README.md
setup.cfg
setup.py
FoodNetX/__init__.py
FoodNetX/database.py
FoodNetX.egg-info/PKG-INFO
FoodNetX.egg-info/SOURCES.txt
FoodNetX.egg-info/dependency_links.txt
FoodNetX.egg-info/requires.txt
FoodNetX.egg-info/top_level.txt