Metadata-Version: 2.1
Name: FoodNetX
Version: 0.1
Summary: Library to create databases using graphs from networkx. Covers the challenge of Foodvisor
Home-page: https://github.com/Jor-G-ete/FoodNetX
Author: Jorge Lopez Marcos
Author-email: jlomar2005@hotmail.com
Maintainer: Jorge Lopez Marcos
Maintainer-email: jlomar2005@hotmail.com
License: GNU General Public License v3.0
Download-URL: https://github.com/Jor-G-ete/FoodNetX/archive/v0.1.tar.gz
Project-URL: Documentation, https://github.com/Jor-G-ete/FoodNetX
Project-URL: Source Code, https://github.com/Jor-G-ete/FoodNetX/blob/master/FoodNetX/database.py
Keywords: python3.7,NeuroSky,Graphs,Trees
Platform: Windows
Classifier: Development Status :: 4 - Beta
Classifier: Intended Audience :: Developers
Classifier: Topic :: Software Development :: Build Tools
Classifier: License :: OSI Approved :: GNU General Public License v3 or later (GPLv3+)
Classifier: Programming Language :: Python :: 3
Classifier: Programming Language :: Python :: 3.7
Classifier: Natural Language :: English
Classifier: Natural Language :: Spanish
Classifier: Operating System :: Microsoft :: Windows :: Windows 10
Classifier: Topic :: Scientific/Engineering :: Medical Science Apps.
Requires-Python: >=3.7
